{
  "version": "3.0.0",
  "flags": {},
  "shapes": [
    {
      "label": "apple",
      "score": null,
      "points": [
        [
          448.0,
          179.0
        ],
        [
          745.0,
          179.0
        ],
        [
          745.0,
          466.0
        ],
        [
          448.0,
          466.0
        ]
      ],
      "group_id": null,
      "description": "",
      "difficult": false,
      "shape_type": "rectangle",
      "flags": {},
      "attributes": {},
      "kie_linking": []
    },
    {
      "label": "coin",
      "score": null,
      "points": [
        [
          61.0,
          400.0
        ],
        [
          169.0,
          400.0
        ],
        [
          169.0,
          503.0
        ],
        [
          61.0,
          503.0
        ]
      ],
      "group_id": null,
      "description": "",
      "difficult": false,
      "shape_type": "rectangle",
      "flags": {},
      "attributes": {},
      "kie_linking": []
    },
    {
      "label": "coin",
      "score": null,
      "points": [
        [
          97.0,
          403.0
        ],
        [
          96.0,
          404.0
        ],
        [
          95.0,
          404.0
        ],
        [
          94.0,
          405.0
        ],
        [
          93.0,
          405.0
        ],
        [
          92.0,
          406.0
        ],
        [
          91.0,
          406.0
        ],
        [
          90.0,
          407.0
        ],
        [
          87.0,
          408.0
        ],
        [
          85.0,
          410.0
        ],
        [
          84.0,
          410.0
        ],
        [
          82.0,
          412.0
        ],
        [
          81.0,
          412.0
        ],
        [
          77.0,
          416.0
        ],
        [
          76.0,
          416.0
        ],
        [
          75.0,
          417.0
        ],
        [
          75.0,
          418.0
        ],
        [
          70.0,
          423.0
        ],
        [
          70.0,
          424.0
        ],
        [
          69.0,
          425.0
        ],
        [
          69.0,
          426.0
        ],
        [
          68.0,
          427.0
        ],
        [
          68.0,
          428.0
        ],
        [
          65.0,
          433.0
        ],
        [
          65.0,
          435.0
        ],
        [
          64.0,
          436.0
        ],
        [
          64.0,
          438.0
        ],
        [
          63.0,
          439.0
        ],
        [
          63.0,
          443.0
        ],
        [
          62.0,
          444.0
        ],
        [
          62.0,
          459.0
        ],
        [
          63.0,
          460.0
        ],
        [
          63.0,
          464.0
        ],
        [
          64.0,
          465.0
        ],
        [
          64.0,
          469.0
        ],
        [
          65.0,
          470.0
        ],
        [
          65.0,
          472.0
        ],
        [
          66.0,
          473.0
        ],
        [
          66.0,
          474.0
        ],
        [
          67.0,
          475.0
        ],
        [
          67.0,
          476.0
        ],
        [
          68.0,
          477.0
        ],
        [
          68.0,
          478.0
        ],
        [
          69.0,
          479.0
        ],
        [
          69.0,
          480.0
        ],
        [
          70.0,
          481.0
        ],
        [
          71.0,
          484.0
        ],
        [
          80.0,
          493.0
        ],
        [
          81.0,
          493.0
        ],
        [
          83.0,
          495.0
        ],
        [
          84.0,
          495.0
        ],
        [
          87.0,
          498.0
        ],
        [
          88.0,
          498.0
        ],
        [
          93.0,
          501.0
        ],
        [
          96.0,
          501.0
        ],
        [
          97.0,
          502.0
        ],
        [
          100.0,
          502.0
        ],
        [
          101.0,
          503.0
        ],
        [
          109.0,
          503.0
        ],
        [
          110.0,
          504.0
        ],
        [
          119.0,
          504.0
        ],
        [
          120.0,
          503.0
        ],
        [
          126.0,
          503.0
        ],
        [
          127.0,
          502.0
        ],
        [
          131.0,
          502.0
        ],
        [
          132.0,
          501.0
        ],
        [
          135.0,
          501.0
        ],
        [
          137.0,
          499.0
        ],
        [
          140.0,
          498.0
        ],
        [
          142.0,
          496.0
        ],
        [
          143.0,
          496.0
        ],
        [
          146.0,
          493.0
        ],
        [
          147.0,
          493.0
        ],
        [
          156.0,
          484.0
        ],
        [
          156.0,
          483.0
        ],
        [
          157.0,
          482.0
        ],
        [
          157.0,
          481.0
        ],
        [
          159.0,
          479.0
        ],
        [
          159.0,
          478.0
        ],
        [
          160.0,
          477.0
        ],
        [
          161.0,
          474.0
        ],
        [
          163.0,
          472.0
        ],
        [
          163.0,
          469.0
        ],
        [
          164.0,
          468.0
        ],
        [
          164.0,
          466.0
        ],
        [
          165.0,
          465.0
        ],
        [
          165.0,
          463.0
        ],
        [
          166.0,
          462.0
        ],
        [
          166.0,
          460.0
        ],
        [
          167.0,
          459.0
        ],
        [
          167.0,
          443.0
        ],
        [
          166.0,
          442.0
        ],
        [
          166.0,
          439.0
        ],
        [
          164.0,
          436.0
        ],
        [
          164.0,
          433.0
        ],
        [
          163.0,
          432.0
        ],
        [
          163.0,
          430.0
        ],
        [
          162.0,
          429.0
        ],
        [
          162.0,
          428.0
        ],
        [
          161.0,
          427.0
        ],
        [
          160.0,
          424.0
        ],
        [
          157.0,
          421.0
        ],
        [
          156.0,
          418.0
        ],
        [
          153.0,
          415.0
        ],
        [
          152.0,
          415.0
        ],
        [
          146.0,
          409.0
        ],
        [
          143.0,
          408.0
        ],
        [
          141.0,
          406.0
        ],
        [
          140.0,
          406.0
        ],
        [
          135.0,
          403.0
        ],
        [
          132.0,
          403.0
        ],
        [
          131.0,
          402.0
        ],
        [
          127.0,
          402.0
        ],
        [
          126.0,
          401.0
        ],
        [
          107.0,
          401.0
        ],
        [
          106.0,
          402.0
        ],
        [
          100.0,
          402.0
        ],
        [
          99.0,
          403.0
        ]
      ],
      "group_id": null,
      "description": "",
      "difficult": false,
      "shape_type": "polygon",
      "flags": {},
      "attributes": {},
      "kie_linking": []
    },
    {
      "label": "apple",
      "score": null,
      "points": [
        [
          683.0,
          198.0
        ],
        [
          661.0,
          188.0
        ],
        [
          631.0,
          181.0
        ],
        [
          601.0,
          181.0
        ],
        [
          579.0,
          183.0
        ],
        [
          547.0,
          192.0
        ],
        [
          534.0,
          199.0
        ],
        [
          527.0,
          201.0
        ],
        [
          514.0,
          209.0
        ],
        [
          484.0,
          236.0
        ],
        [
          467.0,
          264.0
        ],
        [
          459.0,
          281.0
        ],
        [
          459.0,
          285.0
        ],
        [
          454.0,
          296.0
        ],
        [
          450.0,
          314.0
        ],
        [
          448.0,
          343.0
        ],
        [
          449.0,
          371.0
        ],
        [
          454.0,
          392.0
        ],
        [
          469.0,
          422.0
        ],
        [
          479.0,
          434.0
        ],
        [
          490.0,
          444.0
        ],
        [
          508.0,
          455.0
        ],
        [
          515.0,
          456.0
        ],
        [
          538.0,
          464.0
        ],
        [
          559.0,
          466.0
        ],
        [
          606.0,
          467.0
        ],
        [
          632.0,
          465.0
        ],
        [
          641.0,
          462.0
        ],
        [
          649.0,
          462.0
        ],
        [
          657.0,
          459.0
        ],
        [
          668.0,
          458.0
        ],
        [
          693.0,
          446.0
        ],
        [
          707.0,
          436.0
        ],
        [
          726.0,
          408.0
        ],
        [
          737.0,
          378.0
        ],
        [
          742.0,
          345.0
        ],
        [
          740.0,
          299.0
        ],
        [
          736.0,
          278.0
        ],
        [
          728.0,
          256.0
        ],
        [
          718.0,
          236.0
        ],
        [
          704.0,
          217.0
        ]
      ],
      "group_id": null,
      "description": "",
      "difficult": false,
      "shape_type": "polygon",
      "flags": {},
      "attributes": {},
      "kie_linking": []
    },
    {
      "label": "white_plate",
      "score": null,
      "points": [
        [
          219.34751773049643,
          360.6099290780142
        ],
        [
          815.0,
          360.6099290780142
        ],
        [
          815.0,
          520
        ],
        [
          219.34751773049643,
          520
        ]
      ],
      "group_id": null,
      "description": "",
      "difficult": false,
      "shape_type": "rectangle",
      "flags": {},
      "attributes": {},
      "kie_linking": []
    }
  ],
  "imagePath": "apple005S(5).JPG",
  "imageData": null,
  "imageHeight": 612,
  "imageWidth": 816,
  "description": ""
}