{
  "version": "3.0.0",
  "flags": {},
  "shapes": [
    {
      "label": "apple",
      "score": null,
      "points": [
        [
          160.48226950354606,
          243.5886524822695
        ],
        [
          382.468085106383,
          243.5886524822695
        ],
        [
          382.468085106383,
          469.82978723404256
        ],
        [
          160.48226950354606,
          469.82978723404256
        ]
      ],
      "group_id": null,
      "description": "",
      "difficult": false,
      "shape_type": "rectangle",
      "flags": {},
      "attributes": {},
      "kie_linking": []
    },
    {
      "label": "coin",
      "score": null,
      "points": [
        [
          509.0,
          82.0
        ],
        [
          566.0,
          82.0
        ],
        [
          566.0,
          139.0
        ],
        [
          509.0,
          139.0
        ]
      ],
      "group_id": null,
      "description": "",
      "difficult": false,
      "shape_type": "rectangle",
      "flags": {},
      "attributes": {},
      "kie_linking": []
    },
    {
      "label": "apple",
      "score": null,
      "points": [
        [
          286.0,
          247.0
        ],
        [
          277.0,
          247.0
        ],
        [
          276.0,
          248.0
        ],
        [
          258.0,
          250.0
        ],
        [
          243.0,
          255.0
        ],
        [
          222.0,
          266.0
        ],
        [
          204.0,
          280.0
        ],
        [
          189.0,
          295.0
        ],
        [
          179.0,
          308.0
        ],
        [
          171.0,
          324.0
        ],
        [
          171.0,
          327.0
        ],
        [
          168.0,
          336.0
        ],
        [
          168.0,
          341.0
        ],
        [
          167.0,
          342.0
        ],
        [
          167.0,
          350.0
        ],
        [
          166.0,
          351.0
        ],
        [
          168.0,
          374.0
        ],
        [
          172.0,
          385.0
        ],
        [
          173.0,
          391.0
        ],
        [
          176.0,
          398.0
        ],
        [
          179.0,
          402.0
        ],
        [
          180.0,
          406.0
        ],
        [
          189.0,
          419.0
        ],
        [
          203.0,
          433.0
        ],
        [
          226.0,
          453.0
        ],
        [
          228.0,
          453.0
        ],
        [
          244.0,
          461.0
        ],
        [
          252.0,
          462.0
        ],
        [
          262.0,
          465.0
        ],
        [
          270.0,
          465.0
        ],
        [
          271.0,
          466.0
        ],
        [
          288.0,
          465.0
        ],
        [
          289.0,
          464.0
        ],
        [
          293.0,
          464.0
        ],
        [
          303.0,
          461.0
        ],
        [
          325.0,
          449.0
        ],
        [
          338.0,
          439.0
        ],
        [
          348.0,
          429.0
        ],
        [
          349.0,
          426.0
        ],
        [
          354.0,
          420.0
        ],
        [
          362.0,
          403.0
        ],
        [
          365.0,
          400.0
        ],
        [
          374.0,
          380.0
        ],
        [
          375.0,
          372.0
        ],
        [
          376.0,
          371.0
        ],
        [
          376.0,
          366.0
        ],
        [
          377.0,
          365.0
        ],
        [
          377.0,
          342.0
        ],
        [
          376.0,
          341.0
        ],
        [
          376.0,
          336.0
        ],
        [
          375.0,
          335.0
        ],
        [
          374.0,
          328.0
        ],
        [
          370.0,
          319.0
        ],
        [
          369.0,
          314.0
        ],
        [
          364.0,
          304.0
        ],
        [
          349.0,
          281.0
        ],
        [
          334.0,
          267.0
        ],
        [
          314.0,
          255.0
        ],
        [
          312.0,
          255.0
        ],
        [
          305.0,
          251.0
        ],
        [
          302.0,
          251.0
        ],
        [
          293.0,
          248.0
        ],
        [
          287.0,
          248.0
        ]
      ],
      "group_id": null,
      "description": "",
      "difficult": false,
      "shape_type": "polygon",
      "flags": {},
      "attributes": {},
      "kie_linking": []
    },
    {
      "label": "coin",
      "score": null,
      "points": [
        [
          545.0,
          84.0
        ],
        [
          539.0,
          84.0
        ],
        [
          538.0,
          83.0
        ],
        [
          537.0,
          83.0
        ],
        [
          536.0,
          84.0
        ],
        [
          529.0,
          84.0
        ],
        [
          528.0,
          85.0
        ],
        [
          527.0,
          85.0
        ],
        [
          526.0,
          86.0
        ],
        [
          525.0,
          86.0
        ],
        [
          524.0,
          87.0
        ],
        [
          523.0,
          87.0
        ],
        [
          514.0,
          96.0
        ],
        [
          514.0,
          97.0
        ],
        [
          513.0,
          98.0
        ],
        [
          513.0,
          102.0
        ],
        [
          512.0,
          103.0
        ],
        [
          512.0,
          108.0
        ],
        [
          511.0,
          109.0
        ],
        [
          511.0,
          117.0
        ],
        [
          512.0,
          118.0
        ],
        [
          512.0,
          121.0
        ],
        [
          513.0,
          122.0
        ],
        [
          513.0,
          123.0
        ],
        [
          514.0,
          124.0
        ],
        [
          514.0,
          125.0
        ],
        [
          515.0,
          126.0
        ],
        [
          515.0,
          127.0
        ],
        [
          517.0,
          129.0
        ],
        [
          517.0,
          130.0
        ],
        [
          520.0,
          133.0
        ],
        [
          521.0,
          133.0
        ],
        [
          523.0,
          135.0
        ],
        [
          524.0,
          135.0
        ],
        [
          525.0,
          136.0
        ],
        [
          526.0,
          136.0
        ],
        [
          527.0,
          137.0
        ],
        [
          529.0,
          137.0
        ],
        [
          530.0,
          138.0
        ],
        [
          532.0,
          138.0
        ],
        [
          533.0,
          139.0
        ],
        [
          541.0,
          139.0
        ],
        [
          542.0,
          138.0
        ],
        [
          545.0,
          138.0
        ],
        [
          546.0,
          137.0
        ],
        [
          548.0,
          137.0
        ],
        [
          549.0,
          136.0
        ],
        [
          550.0,
          136.0
        ],
        [
          551.0,
          135.0
        ],
        [
          552.0,
          135.0
        ],
        [
          555.0,
          132.0
        ],
        [
          556.0,
          132.0
        ],
        [
          558.0,
          130.0
        ],
        [
          558.0,
          129.0
        ],
        [
          560.0,
          127.0
        ],
        [
          560.0,
          126.0
        ],
        [
          561.0,
          125.0
        ],
        [
          561.0,
          124.0
        ],
        [
          562.0,
          123.0
        ],
        [
          562.0,
          121.0
        ],
        [
          563.0,
          120.0
        ],
        [
          563.0,
          118.0
        ],
        [
          564.0,
          117.0
        ],
        [
          564.0,
          104.0
        ],
        [
          563.0,
          103.0
        ],
        [
          563.0,
          101.0
        ],
        [
          562.0,
          100.0
        ],
        [
          562.0,
          99.0
        ],
        [
          560.0,
          97.0
        ],
        [
          560.0,
          96.0
        ],
        [
          557.0,
          93.0
        ],
        [
          557.0,
          92.0
        ],
        [
          553.0,
          88.0
        ],
        [
          552.0,
          88.0
        ],
        [
          550.0,
          86.0
        ],
        [
          549.0,
          86.0
        ],
        [
          548.0,
          85.0
        ],
        [
          546.0,
          85.0
        ]
      ],
      "group_id": null,
      "description": "",
      "difficult": false,
      "shape_type": "polygon",
      "flags": {},
      "attributes": {},
      "kie_linking": []
    },
    {
      "label": "white_plate",
      "score": null,
      "points": [
        [
          44.87943262411346,
          76.21276595744679
        ],
        [
          547.7163120567376,
          76.21276595744679
        ],
        [
          547.7163120567376,
          577.6312056737588
        ],
        [
          44.87943262411346,
          577.6312056737588
        ]
      ],
      "group_id": null,
      "description": "",
      "difficult": false,
      "shape_type": "rectangle",
      "flags": {},
      "attributes": {},
      "kie_linking": []
    }
  ],
  "imagePath": "apple011T(2).JPG",
  "imageData": null,
  "imageHeight": 612,
  "imageWidth": 816,
  "description": ""
}