{
  "version": "3.0.0",
  "flags": {},
  "shapes": [
    {
      "label": "banana",
      "description": "",
      "points": [
        [
          411.0,
          70.0
        ],
        [
          657.0,
          70.0
        ],
        [
          657.0,
          503.0
        ],
        [
          411.0,
          503.0
        ]
      ],
      "group_id": null,
      "difficult": false,
      "shape_type": "rectangle",
      "flags": {}
    },
    {
      "label": "coin",
      "description": "",
      "points": [
        [
          153.0,
          215.0
        ],
        [
          216.0,
          215.0
        ],
        [
          216.0,
          279.0
        ],
        [
          153.0,
          279.0
        ]
      ],
      "group_id": null,
      "difficult": false,
      "shape_type": "rectangle",
      "flags": {}
    }
  ],
  "imagePath": "banana014T(1).JPG",
  "imageData": null,
  "imageHeight": 612,
  "imageWidth": 816
}