{
  "version": "3.0.0",
  "flags": {},
  "shapes": [
    {
      "label": "egg",
      "description": "",
      "points": [
        [
          317.0,
          307.0
        ],
        [
          458.0,
          307.0
        ],
        [
          458.0,
          408.0
        ],
        [
          317.0,
          408.0
        ]
      ],
      "group_id": null,
      "difficult": false,
      "shape_type": "rectangle",
      "flags": {}
    },
    {
      "label": "coin",
      "description": "",
      "points": [
        [
          125.0,
          253.0
        ],
        [
          186.0,
          253.0
        ],
        [
          186.0,
          312.0
        ],
        [
          125.0,
          312.0
        ]
      ],
      "group_id": null,
      "difficult": false,
      "shape_type": "rectangle",
      "flags": {}
    }
  ],
  "imagePath": "egg004T(1).JPG",
  "imageData": null,
  "imageHeight": 612,
  "imageWidth": 816
}