{
  "version": "3.0.0",
  "flags": {},
  "shapes": [
    {
      "label": "egg",
      "description": "",
      "points": [
        [
          539.0,
          263.0
        ],
        [
          665.0,
          263.0
        ],
        [
          665.0,
          415.0
        ],
        [
          539.0,
          415.0
        ]
      ],
      "group_id": null,
      "difficult": false,
      "shape_type": "rectangle",
      "flags": {}
    },
    {
      "label": "coin",
      "description": "",
      "points": [
        [
          138.0,
          300.0
        ],
        [
          200.0,
          300.0
        ],
        [
          200.0,
          361.0
        ],
        [
          138.0,
          361.0
        ]
      ],
      "group_id": null,
      "difficult": false,
      "shape_type": "rectangle",
      "flags": {}
    }
  ],
  "imagePath": "egg002T(2).JPG",
  "imageData": null,
  "imageHeight": 612,
  "imageWidth": 816
}