{
  "version": "3.0.0",
  "flags": {},
  "shapes": [
    {
      "label": "fired_dough_twist",
      "description": "",
      "points": [
        [
          453.0,
          272.0
        ],
        [
          731.0,
          272.0
        ],
        [
          731.0,
          385.0
        ],
        [
          453.0,
          385.0
        ]
      ],
      "group_id": null,
      "difficult": false,
      "shape_type": "rectangle",
      "flags": {}
    },
    {
      "label": "coin",
      "description": "",
      "points": [
        [
          140.0,
          347.0
        ],
        [
          215.0,
          347.0
        ],
        [
          215.0,
          418.0
        ],
        [
          140.0,
          418.0
        ]
      ],
      "group_id": null,
      "difficult": false,
      "shape_type": "rectangle",
      "flags": {}
    }
  ],
  "imagePath": "fired_dough_twist005S(2).JPG",
  "imageData": null,
  "imageHeight": 612,
  "imageWidth": 816
}