{
  "version": "3.0.0",
  "flags": {},
  "shapes": [
    {
      "label": "lemon",
      "description": "",
      "points": [
        [
          466.0,
          204.0
        ],
        [
          648.0,
          204.0
        ],
        [
          648.0,
          414.0
        ],
        [
          466.0,
          414.0
        ]
      ],
      "group_id": null,
      "difficult": false,
      "shape_type": "rectangle",
      "flags": {}
    },
    {
      "label": "coin",
      "description": "",
      "points": [
        [
          120.0,
          163.0
        ],
        [
          192.0,
          163.0
        ],
        [
          192.0,
          232.0
        ],
        [
          120.0,
          232.0
        ]
      ],
      "group_id": null,
      "difficult": false,
      "shape_type": "rectangle",
      "flags": {}
    }
  ],
  "imagePath": "lemon002T(13).JPG",
  "imageData": null,
  "imageHeight": 612,
  "imageWidth": 816
}