{
  "version": "3.0.0",
  "flags": {},
  "shapes": [
    {
      "label": "lemon",
      "description": "",
      "points": [
        [
          477.0,
          315.0
        ],
        [
          607.0,
          315.0
        ],
        [
          607.0,
          442.0
        ],
        [
          477.0,
          442.0
        ]
      ],
      "group_id": null,
      "difficult": false,
      "shape_type": "rectangle",
      "flags": {}
    },
    {
      "label": "coin",
      "description": "",
      "points": [
        [
          163.0,
          397.0
        ],
        [
          221.0,
          397.0
        ],
        [
          221.0,
          459.0
        ],
        [
          163.0,
          459.0
        ]
      ],
      "group_id": null,
      "difficult": false,
      "shape_type": "rectangle",
      "flags": {}
    }
  ],
  "imagePath": "lemon002S(14).JPG",
  "imageData": null,
  "imageHeight": 612,
  "imageWidth": 816
}