{
  "version": "3.0.0",
  "flags": {},
  "shapes": [
    {
      "label": "litchi",
      "description": "",
      "points": [
        [
          473.0,
          307.0
        ],
        [
          584.0,
          307.0
        ],
        [
          584.0,
          410.0
        ],
        [
          473.0,
          410.0
        ]
      ],
      "group_id": null,
      "difficult": false,
      "shape_type": "rectangle",
      "flags": {}
    },
    {
      "label": "coin",
      "description": "",
      "points": [
        [
          226.0,
          349.0
        ],
        [
          291.0,
          349.0
        ],
        [
          291.0,
          411.0
        ],
        [
          226.0,
          411.0
        ]
      ],
      "group_id": null,
      "difficult": false,
      "shape_type": "rectangle",
      "flags": {}
    }
  ],
  "imagePath": "litchi004S(1).JPG",
  "imageData": null,
  "imageHeight": 612,
  "imageWidth": 816
}