{
  "version": "3.0.0",
  "flags": {},
  "shapes": [
    {
      "label": "litchi",
      "description": "",
      "points": [
        [
          476.0,
          297.0
        ],
        [
          583.0,
          297.0
        ],
        [
          583.0,
          410.0
        ],
        [
          476.0,
          410.0
        ]
      ],
      "group_id": null,
      "difficult": false,
      "shape_type": "rectangle",
      "flags": {}
    },
    {
      "label": "coin",
      "description": "",
      "points": [
        [
          286.0,
          342.0
        ],
        [
          348.0,
          342.0
        ],
        [
          348.0,
          404.0
        ],
        [
          286.0,
          404.0
        ]
      ],
      "group_id": null,
      "difficult": false,
      "shape_type": "rectangle",
      "flags": {}
    }
  ],
  "imagePath": "litchi001S(1).JPG",
  "imageData": null,
  "imageHeight": 612,
  "imageWidth": 816
}