{
  "version": "3.0.0",
  "flags": {},
  "shapes": [
    {
      "label": "mooncake",
      "description": "",
      "points": [
        [
          433.0,
          305.0
        ],
        [
          607.0,
          305.0
        ],
        [
          607.0,
          375.0
        ],
        [
          433.0,
          375.0
        ]
      ],
      "group_id": null,
      "difficult": false,
      "shape_type": "rectangle",
      "flags": {}
    },
    {
      "label": "coin",
      "description": "",
      "points": [
        [
          109.0,
          330.0
        ],
        [
          170.0,
          330.0
        ],
        [
          170.0,
          392.0
        ],
        [
          109.0,
          392.0
        ]
      ],
      "group_id": null,
      "difficult": false,
      "shape_type": "rectangle",
      "flags": {}
    }
  ],
  "imagePath": "mooncake006S(3).JPG",
  "imageData": null,
  "imageHeight": 612,
  "imageWidth": 816
}