{
  "version": "3.0.0",
  "flags": {},
  "shapes": [
    {
      "label": "orange",
      "description": "",
      "points": [
        [
          303.0,
          96.0
        ],
        [
          427.0,
          96.0
        ],
        [
          427.0,
          215.0
        ],
        [
          303.0,
          215.0
        ]
      ],
      "group_id": null,
      "difficult": false,
      "shape_type": "rectangle",
      "flags": {}
    },
    {
      "label": "coin",
      "description": "",
      "points": [
        [
          96.0,
          188.0
        ],
        [
          144.0,
          188.0
        ],
        [
          144.0,
          233.0
        ],
        [
          96.0,
          233.0
        ]
      ],
      "group_id": null,
      "difficult": false,
      "shape_type": "rectangle",
      "flags": {}
    }
  ],
  "imagePath": "orange013S(1).JPG",
  "imageData": null,
  "imageHeight": 378,
  "imageWidth": 504
}