{
  "version": "3.0.0",
  "flags": {},
  "shapes": [
    {
      "label": "orange",
      "description": "",
      "points": [
        [
          265.0,
          119.0
        ],
        [
          444.0,
          119.0
        ],
        [
          444.0,
          354.0
        ],
        [
          265.0,
          354.0
        ]
      ],
      "group_id": null,
      "difficult": false,
      "shape_type": "rectangle",
      "flags": {}
    },
    {
      "label": "coin",
      "description": "",
      "points": [
        [
          674.0,
          276.0
        ],
        [
          733.0,
          276.0
        ],
        [
          733.0,
          336.0
        ],
        [
          674.0,
          336.0
        ]
      ],
      "group_id": null,
      "difficult": false,
      "shape_type": "rectangle",
      "flags": {}
    }
  ],
  "imagePath": "orange001T(1).JPG",
  "imageData": null,
  "imageHeight": 612,
  "imageWidth": 816
}