{
  "version": "3.0.0",
  "flags": {},
  "shapes": [
    {
      "label": "peach",
      "description": "",
      "points": [
        [
          431.0,
          255.0
        ],
        [
          593.0,
          255.0
        ],
        [
          593.0,
          407.0
        ],
        [
          431.0,
          407.0
        ]
      ],
      "group_id": null,
      "difficult": false,
      "shape_type": "rectangle",
      "flags": {}
    },
    {
      "label": "coin",
      "description": "",
      "points": [
        [
          111.0,
          197.0
        ],
        [
          176.0,
          197.0
        ],
        [
          176.0,
          257.0
        ],
        [
          111.0,
          257.0
        ]
      ],
      "group_id": null,
      "difficult": false,
      "shape_type": "rectangle",
      "flags": {}
    }
  ],
  "imagePath": "peach001T(11).JPG",
  "imageData": null,
  "imageHeight": 612,
  "imageWidth": 816
}