{
  "version": "3.0.0",
  "flags": {},
  "shapes": [
    {
      "label": "plum",
      "description": "",
      "points": [
        [
          497.0,
          198.0
        ],
        [
          702.0,
          198.0
        ],
        [
          702.0,
          375.0
        ],
        [
          497.0,
          375.0
        ]
      ],
      "group_id": null,
      "difficult": false,
      "shape_type": "rectangle",
      "flags": {}
    },
    {
      "label": "coin",
      "description": "",
      "points": [
        [
          173.0,
          314.0
        ],
        [
          251.0,
          314.0
        ],
        [
          251.0,
          381.0
        ],
        [
          173.0,
          381.0
        ]
      ],
      "group_id": null,
      "difficult": false,
      "shape_type": "rectangle",
      "flags": {}
    }
  ],
  "imagePath": "plum001S(15).JPG",
  "imageData": null,
  "imageHeight": 612,
  "imageWidth": 816
}