{
  "version": "3.0.0",
  "flags": {},
  "shapes": [
    {
      "label": "tomato",
      "description": "",
      "points": [
        [
          431.0,
          276.0
        ],
        [
          599.0,
          276.0
        ],
        [
          599.0,
          412.0
        ],
        [
          431.0,
          412.0
        ]
      ],
      "group_id": null,
      "difficult": false,
      "shape_type": "rectangle",
      "flags": {}
    },
    {
      "label": "coin",
      "description": "",
      "points": [
        [
          136.0,
          373.0
        ],
        [
          209.0,
          373.0
        ],
        [
          209.0,
          429.0
        ],
        [
          136.0,
          429.0
        ]
      ],
      "group_id": null,
      "difficult": false,
      "shape_type": "rectangle",
      "flags": {}
    }
  ],
  "imagePath": "tomato002S(1).JPG",
  "imageData": null,
  "imageHeight": 612,
  "imageWidth": 816
}